plugin_kube/__init__.py
one_cli_plugin_kube-0.5.2.dist-info/LICENSE
one_cli_plugin_kube-0.5.2.dist-info/METADATA
one_cli_plugin_kube-0.5.2.dist-info/WHEEL
one_cli_plugin_kube-0.5.2.dist-info/top_level.txt
one_cli_plugin_kube-0.5.2.dist-info/RECORD
