Metadata-Version: 2.1
Name: one-cli-plugin-kube
Version: 0.5.2
Summary: This is a one-cli plugin that adds Kubernetes tools alias to the CLI.
Home-page: https://github.com/DNXLabs/plugin-kube
Author: DNX Solutions
Author-email: contact@dnx.solutions
License: Apache License 2.0
Platform: UNKNOWN
Classifier: Development Status :: 5 - Production/Stable
Classifier: Intended Audience :: Developers
Classifier: Intended Audience :: System Administrators
Classifier: Natural Language :: English
Classifier: License :: OSI Approved :: Apache Software License
Classifier: Programming Language :: Python
Classifier: Programming Language :: Python :: 3
Classifier: Programming Language :: Python :: 3.4
Classifier: Programming Language :: Python :: 3.5
Classifier: Programming Language :: Python :: 3.6
Classifier: Programming Language :: Python :: 3.7
Classifier: Programming Language :: Python :: 3.8
Requires-Python: >=3.6
